codevault/__init__.py
codevault/cli.py
codevault/vault.py
selfvcs-1.0.0.dist-info/METADATA
selfvcs-1.0.0.dist-info/WHEEL
selfvcs-1.0.0.dist-info/entry_points.txt
selfvcs-1.0.0.dist-info/top_level.txt
selfvcs-1.0.0.dist-info/RECORD
